MANIFEST.in
README
requirements.txt
setup.py
Logrdis.egg-info/PKG-INFO
Logrdis.egg-info/SOURCES.txt
Logrdis.egg-info/dependency_links.txt
Logrdis.egg-info/entry_points.txt
Logrdis.egg-info/requires.txt
Logrdis.egg-info/top_level.txt
logrdis/__init__.py
logrdis/_socket3.py
logrdis/config.py
logrdis/core.py
logrdis/db.py
logrdis/log.py
logrdis/socket.py
logrdis/util.py
tests/test.yml