Metadata-Version: 1.0
Name: Logrdis
Version: 0.3.0
Summary: A fully configurable stream redirector from a socket to a database
Home-page: https://github.com/Carbyne-Solutions/logrdis
Author: Matt Daue
Author-email: mdaue@carbyne.solutions
License: BSD-4-Clause
Keywords: log stream sql redirect
Platform: UNKNOWN
